Metadata-Version: 2.4
Name: iflow-mcp_batianvolyc_telegram-mcp-server
Version: 0.2.4
Summary: Remote control Claude Code via Telegram - MCP Server with Dynamic Buttons
Author-email: Ray Volcy <volycu@gmail.com>
License: MIT
Project-URL: Homepage, https://github.com/batianVolyc/telegram-mcp-server
Project-URL: Documentation, https://github.com/batianVolyc/telegram-mcp-server#readme
Project-URL: Repository, https://github.com/batianVolyc/telegram-mcp-server
Project-URL: Issues, https://github.com/batianVolyc/telegram-mcp-server/issues
Keywords: mcp,telegram,claude,ai,automation
Classifier: Development Status :: 4 - Beta
Classifier: Intended Audience :: Developers
Classifier: License :: OSI Approved :: MIT License
Classifier: Programming Language :: Python :: 3
Classifier: Programming Language :: Python :: 3.10
Classifier: Programming Language :: Python :: 3.11
Classifier: Programming Language :: Python :: 3.12
Classifier: Topic :: Communications :: Chat
Classifier: Topic :: Software Development :: Libraries :: Python Modules
Requires-Python: >=3.10
License-File: LICENSE
Requires-Dist: mcp>=1.0.0
Requires-Dist: python-telegram-bot>=21.0
Requires-Dist: httpx>=0.24.0
Requires-Dist: toml>=0.10.0
Provides-Extra: dev
Requires-Dist: pytest>=7.0; extra == "dev"
Requires-Dist: pytest-asyncio>=0.21.0; extra == "dev"
Requires-Dist: black>=23.0; extra == "dev"
Requires-Dist: ruff>=0.1.0; extra == "dev"
Dynamic: license-file
